ghx/__init__.py
ghx/__main__.py
ghx/cli.py
ghx-0.1.1.dist-info/METADATA
ghx-0.1.1.dist-info/WHEEL
ghx-0.1.1.dist-info/entry_points.txt
ghx-0.1.1.dist-info/top_level.txt
ghx-0.1.1.dist-info/RECORD
